<annotation>
	<folder>my-project-name</folder>
	<filename>stand (7).jpg</filename>
	<path>/my-project-name/stand (7).jpg</path>
	<source>
		<database>Unspecified</database>
	</source>
	<size>
		<width>300</width>
		<height>240</height>
		<depth>3</depth>
	</size>
	<object>
		<name>stand</name>
		<pose>Unspecified</pose>
		<truncated>0</truncated>
		<difficult>0</difficult>
		<bndbox>
			<xmin>110</xmin>
			<ymin>16</ymin>
			<xmax>222</xmax>
			<ymax>224</ymax>
		</bndbox>
	</object>
</annotation>