<annotation>
	<folder>my-project-name</folder>
	<filename>stand (18).jpg</filename>
	<path>/my-project-name/stand (18).jpg</path>
	<source>
		<database>Unspecified</database>
	</source>
	<size>
		<width>2160</width>
		<height>3840</height>
		<depth>3</depth>
	</size>
	<object>
		<name>stand</name>
		<pose>Unspecified</pose>
		<truncated>0</truncated>
		<difficult>0</difficult>
		<bndbox>
			<xmin>223</xmin>
			<ymin>227</ymin>
			<xmax>805</xmax>
			<ymax>3194</ymax>
		</bndbox>
	</object>
	<object>
		<name>sit</name>
		<pose>Unspecified</pose>
		<truncated>0</truncated>
		<difficult>0</difficult>
		<bndbox>
			<xmin>978</xmin>
			<ymin>1010</ymin>
			<xmax>2125</xmax>
			<ymax>3494</ymax>
		</bndbox>
	</object>
</annotation>