<annotation>
	<folder>my-project-name</folder>
	<filename>stand (32).jpg</filename>
	<path>/my-project-name/stand (32).jpg</path>
	<source>
		<database>Unspecified</database>
	</source>
	<size>
		<width>809</width>
		<height>1080</height>
		<depth>3</depth>
	</size>
	<object>
		<name>stand</name>
		<pose>Unspecified</pose>
		<truncated>0</truncated>
		<difficult>0</difficult>
		<bndbox>
			<xmin>458</xmin>
			<ymin>225</ymin>
			<xmax>593</xmax>
			<ymax>532</ymax>
		</bndbox>
	</object>
</annotation>